UdeyTrajectory/__init__.py
UdeyTrajectory/pattern1.json
UdeyTrajectory/pattern2.json
UdeyTrajectory/pattern3.json
udeytrajectory-0.1.2.dist-info/METADATA
udeytrajectory-0.1.2.dist-info/WHEEL
udeytrajectory-0.1.2.dist-info/top_level.txt
udeytrajectory-0.1.2.dist-info/RECORD
